contactbwc
contactbwc_ta
